loupepy/__init__.py
loupepy/convert.py
loupepy/setup.py
loupepy/utils.py
loupepy-1.1.1.dist-info/METADATA
loupepy-1.1.1.dist-info/WHEEL
loupepy-1.1.1.dist-info/entry_points.txt
loupepy-1.1.1.dist-info/RECORD
