Metadata-Version: 2.4
Name: loupepy
Version: 1.1.1
Summary: A python package for generating 10x cloupe files from anndata objects
Project-URL: Homepage, https://github.com/linearparadox/loupepy
Project-URL: Issues, https://github.com/linearparadox/loupepy/issues
Author-email: Alexei Martsinkovskiy <alexei.martsinkovskiy@gmail.com>
License-Expression: MIT
Classifier: Operating System :: OS Independent
Classifier: Programming Language :: Python :: 3
Requires-Python: >=3.10
Requires-Dist: anndata>=0.11.4
Requires-Dist: certifi>=2025.4.26
